booking_core
